confidential/__init__.py
confidential/exceptions.py
confidential/secrets_manager.py
confidential/utils.py
confidential-2.3.1.dist-info/entry_points.txt
confidential-2.3.1.dist-info/LICENSE
confidential-2.3.1.dist-info/WHEEL
confidential-2.3.1.dist-info/METADATA
confidential-2.3.1.dist-info/RECORD
